rks/__init__.py
rks/analysis.py
rks/display.py
rks/main.py
rks/redis_utils.py
rks-1.0.0.dist-info/METADATA
rks-1.0.0.dist-info/WHEEL
rks-1.0.0.dist-info/entry_points.txt
rks-1.0.0.dist-info/top_level.txt
rks-1.0.0.dist-info/RECORD
